[
    {
        "product name": "Креветки Королевские 26/30 очищенные",
        "product cost": "\nЦена за 1 шт\n\n6 100 тг.\n\n",
        "product city": "Алматы"
    },
    {
        "product name": "Креветка Королевская 31/40 очищенная",
        "product cost": "\nЦена за 1 шт\n\n5 900 тг.\n\n",
        "product city": "Алматы"
    },
    {
        "product name": "Лангустины в панцире с головой, размер 21-30",
        "product cost": "\nЦена за 1 кг\n\n6 500 тг.\n\n",
        "product city": "Алматы"
    },
    {
        "product name": "Креветка Королевская  21/25, в панцире без головы",
        "product cost": "\nЦена за 1 шт\n\n5 500 тг.\n\n",
        "product city": "Алматы"
    },
    {
        "product name": "Чука салат замороженный",
        "product cost": "\nЦена за 1 шт\n\n2 800 тг.\n\n",
        "product city": "Алматы"
    },
    {
        "product name": "Креветка Арктическая, 70/90,  Гренландия",
        "product cost": "\nЦена за 1 кг\n\n6 700 тг.\n\n",
        "product city": "Алматы"
    },
    {
        "product name": "Креветка Ваннамей 16/20 в панцире б/г ",
        "product cost": "\nЦена за 1 шт\n\n5 700 тг.\n\n",
        "product city": "Алматы"
    },
    {
        "product name": "Лангустины в Панцире с головой, размер 10-20",
        "product cost": "\nЦена за 1 кг\n\n7 200 тг.\n\n",
        "product city": "Алматы"
    },
    {
        "product name": "Креветка  Салатная 100/200, глазурь 40%",
        "product cost": "\nЦена за 1 шт\n\n3 900 тг.\n\n",
        "product city": "Алматы"
    },
    {
        "product name": "Креветка Северная, 90/120,  Гренландия",
        "product cost": "\nЦена за 1 кг\n\n3 990 тг.\n5400\n\n",
        "product city": "Алматы"
    },
    {
        "product name": "Лангустины в панцире без головы, размер 30 - 50, уп. 2 кг",
        "product cost": "\nЦена за 1 кг\n\n6 500 тг.\n\n",
        "product city": "Алматы"
    },
    {
        "product name": "Креветка Тигровая  с головой 16/20",
        "product cost": "\nЦена за 1 шт\n\n9 000 тг.\n\n",
        "product city": "Алматы"
    },
    {
        "product name": "Креветка Тигровая 8/12  с головой",
        "product cost": "\nЦена за 1 шт\n\n12 000 тг.\n\n",
        "product city": "Алматы"
    },
    {
        "product name": "Креветка Королевская Блочная, в панцире 21/25",
        "product cost": "\nЦена за 1 шт\n\n15 000 тг.\n\n",
        "product city": "Алматы"
    },
    {
        "product name": "Креветка Risma Премиум глазурь 7%",
        "product cost": "\nЦена за 1 шт\n\n6 000 тг.\n\n",
        "product city": "Алматы"
    }
]